MANIFEST.in
setup.py
HiveMind_PtT.egg-info/PKG-INFO
HiveMind_PtT.egg-info/SOURCES.txt
HiveMind_PtT.egg-info/dependency_links.txt
HiveMind_PtT.egg-info/entry_points.txt
HiveMind_PtT.egg-info/requires.txt
HiveMind_PtT.egg-info/top_level.txt
mycroft_ptt/__init__.py
mycroft_ptt/__main__.py
mycroft_ptt/playback.py
mycroft_ptt/configuration/__init__.py
mycroft_ptt/res/snd/listening_error.mp3
mycroft_ptt/res/snd/start_listening.wav
mycroft_ptt/speech/__init__.py
mycroft_ptt/speech/listener.py
mycroft_ptt/speech/mic.py
mycroft_ptt/speech/signal.py