Metadata-Version: 1.0
Name: HiveMind-PtT
Version: 0.1.6
Summary: Mycroft Push to Talk Satellite
Home-page: https://github.com/JarbasHiveMind/HiveMind-PTT
Author: jarbasAI
Author-email: jarbasai@mailfence.com
License: Apache2
Platform: UNKNOWN
